MANIFEST.in
README.md
setup.py
libtoml/__init__.py
libtoml/compiler.py
libtoml/parser.py
libtoml/test.py
libtoml.egg-info/PKG-INFO
libtoml.egg-info/SOURCES.txt
libtoml.egg-info/dependency_links.txt
libtoml.egg-info/not-zip-safe
libtoml.egg-info/requires.txt
libtoml.egg-info/top_level.txt