Metadata-Version: 1.0
Name: libtoml
Version: 1.0
Summary: 
